penquins/__init__.py
penquins/penquins.py
penquins-2.4.1.dist-info/LICENSE
penquins-2.4.1.dist-info/METADATA
penquins-2.4.1.dist-info/WHEEL
penquins-2.4.1.dist-info/top_level.txt
penquins-2.4.1.dist-info/RECORD
